setup.cfg
setup.py
postmark/__init__.py
postmark/api_client.py
postmark/configuration.py
postmark/rest.py
postmark.egg-info/PKG-INFO
postmark.egg-info/SOURCES.txt
postmark.egg-info/dependency_links.txt
postmark.egg-info/requires.txt
postmark.egg-info/top_level.txt
postmark/apis/__init__.py
postmark/apis/bounces_api_api.py
postmark/apis/inbound_rules_api_api.py
postmark/apis/messages_api_api.py
postmark/apis/postmark_api.py
postmark/apis/sending_api_api.py
postmark/apis/server_configuration_api_api.py
postmark/apis/stats_api_api.py
postmark/apis/tag_triggers_api_api.py
postmark/apis/templates_api_api.py
postmark/models/__init__.py
postmark/models/attachment.py
postmark/models/attachment_collection.py
postmark/models/bounce_activation_response.py
postmark/models/bounce_count_element.py
postmark/models/bounce_dump_response.py
postmark/models/bounce_info_response.py
postmark/models/bounce_search_response.py
postmark/models/create_inbound_rule_request.py
postmark/models/create_template_request.py
postmark/models/delivery_stats_response.py
postmark/models/edit_server_configuration_request.py
postmark/models/edit_tag_trigger_request.py
postmark/models/edit_template_request.py
postmark/models/email.py
postmark/models/email_attachments.py
postmark/models/email_headers.py
postmark/models/email_name_address_pair.py
postmark/models/email_with_template_request.py
postmark/models/emailwith_template.py
postmark/models/extended_message_open_event_information.py
postmark/models/extended_message_open_event_information_client.py
postmark/models/extended_message_open_event_information_geo.py
postmark/models/extended_message_open_event_information_os.py
postmark/models/header_collection.py
postmark/models/inbound_message_detail.py
postmark/models/inbound_message_full_details_response.py
postmark/models/inbound_message_full_details_response_from_full.py
postmark/models/inbound_search_response.py
postmark/models/inline_response_200.py
postmark/models/inline_response_200_1.py
postmark/models/inline_response_200_1_days.py
postmark/models/inline_response_200_2.py
postmark/models/inline_response_200_2_days.py
