Metadata-Version: 1.1
Name: postmark
Version: 1.0.0
Summary: Postmark API
Home-page: UNKNOWN
Author: Jonathan Kosgei
Author-email: jonathan@saharacluster.com
License: UNKNOWN
Download-URL: https://github.com/jonathan-kosgei/postmark/archive/1.0.tar.gz
Keywords: Swagger,Postmark API
Platform: UNKNOWN
